pkg_15903/__init__.py
pkg_15903/__main__.py
pkg_15903/run.py
pkg_15903-0.1.100.dist-info/licenses/LICENSE
pkg_15903-0.1.100.dist-info/METADATA
pkg_15903-0.1.100.dist-info/WHEEL
pkg_15903-0.1.100.dist-info/entry_points.txt
pkg_15903-0.1.100.dist-info/top_level.txt
pkg_15903-0.1.100.dist-info/RECORD
