Metadata-Version: 2.4
Name: pkg-15903
Version: 0.1.100
Author-email: developers <developers@tagdots.com>
Project-URL: Changelog, https://www.notavailable.com/changelog
Project-URL: Documentation, https://www.notavailable.com/doc
Project-URL: Homepage, https://www.notavailable.com
Classifier: Intended Audience :: Developers
Classifier: Programming Language :: Python :: 3 :: Only
Classifier: Programming Language :: Python :: 3.12
Classifier: Programming Language :: Python :: 3.13
Classifier: Programming Language :: Python :: 3.14
Classifier: Topic :: Software Development :: Build Tools
Requires-Python: >=3.12.10
License-File: LICENSE
Requires-Dist: click==8.3.0
Requires-Dist: click-option-group==0.5.9
Requires-Dist: requests==2.32.5
Requires-Dist: setuptools==80.9.0
Requires-Dist: virtualenv==20.35.3
Provides-Extra: test
Requires-Dist: build; extra == "test"
Requires-Dist: commitizen; extra == "test"
Requires-Dist: coverage; extra == "test"
Requires-Dist: flake8; extra == "test"
Requires-Dist: isort; extra == "test"
Requires-Dist: pre-commit; extra == "test"
Requires-Dist: pyscan-rs; extra == "test"
Requires-Dist: twine; extra == "test"
Dynamic: license-file
